LICENSE
modelator/.python-version
modelator/Model.py
modelator/ModelMonitor.py
modelator/ModelResult.py
modelator/ModelShell.py
modelator/__init__.py
modelator/__main__.py
modelator/_version.py
modelator/checker/CheckResult.py
modelator/checker/check.py
modelator/checker/simulate.py
modelator/cli/__init__.py
modelator/cli/model_config_file.py
modelator/cli/model_file.py
modelator/const_values.py
modelator/itf.py
modelator/modelator_shell.py
modelator/monitors/content.py
modelator/monitors/html_monitor.py
modelator/monitors/html_writer.py
modelator/monitors/markdown_monitor.py
modelator/monitors/markdown_writer.py
modelator/monitors/templates/html_monitor.html
modelator/monitors/templates/html_section.html
modelator/monitors/templates/html_section_entry.html
modelator/monitors/templates/html_table.html
modelator/monitors/templates/html_trace.html
modelator/parse.py
modelator/pytest/__init__.py
modelator/pytest/decorators.py
modelator/samples/AlarmClock.tla
modelator/samples/Hello.cfg
modelator/samples/Hello.tla
modelator/samples/HelloFlawed.tla
modelator/samples/HelloFlawedType.tla
modelator/samples/HelloFull.config.toml
modelator/samples/HelloFull.tla
modelator/samples/HelloFull1.itf.json
modelator/samples/HelloInv.tla
modelator/samples/HelloWorld.tla
modelator/samples/HourClock.tla
modelator/samples/HourClockTraits.tla
modelator/samples/helloConfig.json
modelator/samples/helloModel.json
modelator/typecheck.py
modelator/utils/ErrorMessage.py
modelator/utils/apalache_helpers.py
modelator/utils/apalache_jar.py
modelator/utils/helpers.py
modelator/utils/model_exceptions.py
modelator/utils/modelator_helpers.py
modelator/utils/tla_helpers.py
modelator/utils/tlc_helpers.py
modelator-0.6.6.dist-info/entry_points.txt
modelator-0.6.6.dist-info/LICENSE
modelator-0.6.6.dist-info/WHEEL
modelator-0.6.6.dist-info/METADATA
modelator-0.6.6.dist-info/RECORD
