Metadata-Version: 2.1
Name: modelator
Version: 0.6.6
Summary: Framework for Model Based Testing
Home-page: https://github.com/informalsystems/atomkraft
License: Apache-2.0
Keywords: testing,model based testing,formal method,model checker,tla,apalache,tlc
Author: Andrey Kuprianov
Author-email: andrey@informal.systems
Requires-Python: >=3.8,<4.0
Classifier: License :: OSI Approved :: Apache Software License
Classifier: Programming Language :: Python :: 3
Classifier: Programming Language :: Python :: 3.8
Classifier: Programming Language :: Python :: 3.9
Classifier: Programming Language :: Python :: 3.10
Classifier: Programming Language :: Python :: 3.11
Classifier: Programming Language :: Python :: 3 :: Only
Classifier: Topic :: Software Development :: Testing
Requires-Dist: appdirs (>=1.4.4,<2.0.0)
Requires-Dist: deepdiff (>=6.2.1,<7.0.0)
Requires-Dist: modelator-py (>=0.2.6,<0.3.0)
Requires-Dist: munch (>=2.5.0,<3.0.0)
Requires-Dist: pyrsistent (>=0.19.2,<0.20.0)
Requires-Dist: rich (>=12.6.0,<13.0.0)
Requires-Dist: semver (>=2.13.0,<3.0.0)
Requires-Dist: tabulate (>=0.9.0,<0.10.0)
Requires-Dist: toml (>=0.10.2,<0.11.0)
Requires-Dist: typer[all] (>=0.7.0,<0.8.0)
Requires-Dist: typing-extensions (>=4.4.0,<5.0.0)
Requires-Dist: watchdog (>=2.1.9,<3.0.0)
Requires-Dist: wget (>=3.2,<4.0)
Project-URL: Repository, https://github.com/informalsystems/atomkraft
